{
  "caption": "The Golden Gate Bridge opening to the public for the first time back in 1937, and yes, it almost collapsed",
  "ground_truth": 1,
  "internal_check": {
    "textual_entities": [
      {
        "entity": "B-LOC",
        "word": "South"
      },
      {
        "entity": "I-LOC",
        "word": "Tower"
      },
      {
        "entity": "B-LOC",
        "word": "Golden"
      },
      {
        "entity": "I-LOC",
        "word": "Gate"
      },
      {
        "entity": "I-LOC",
        "word": "Bridge"
      }
    ],
    "result": {
      "verdict": true
    }
  },
  "external_check": {
    "candidates": [
      {
        "authors": [
          "David Mikkelson"
        ],
        "title": "Is This a Photo of the Golden Gate Bridge's 1937 Opening?",
        "date": "2020-01-15T08:50:06",
        "content": 