{
  "caption": "The picture dated from World War II and captured a soldier carrying the animal in order to keep it from inadvertently tripping landmines and killing everyone around it",
  "ground_truth": 1,
  "internal_check": {
    "textual_entities": [
      {
        "entity": "B-MISC",
        "word": "Algerian"
      },
      {
        "entity": "I-MISC",
        "word": "War"
      },
      {
        "entity": "B-MISC",
        "word": "French"
      },
      {
        "entity": "B-LOC",
        "word": "Colonial"
      },
      {
        "entity": "I-LOC",
        "word": "Algeria"
      },
      {
        "entity": "B-ORG",
        "word": "French"
      },
      {
        "entity": "B-ORG",
        "word": "Foreign"
      },
      {
        "entity": "I-ORG",
        "word": "Legion"
      }
    ],
    "result": {
      "verdict": false
    }
  },
  "external_check": {
    "candidates": [],
    "result": {
      "confidence_score": 3,
      "explanation": "This assessment is knowledge-based. The caption is plausible; soldiers in WWII did face the danger of landmines.  It's believable that a soldier might carry a small animal to prevent it from triggering a mine. However, without external evidence, it's impossible to verify the specific event described.  There is no way to confirm the date or the exact circumstances depicted in the caption. The lack of specifics and verifiable details lowers confidence.",
      "supporting_evidence": [
        "World War II involved extensive use of landmines.",
        "Soldiers frequently encountered animals in war zones.",
        "Carrying a small animal to prevent it from triggering a landmine is a conceivable action."
      ]
    }
  },
  "final_result": {
    "OOC": true,
    "confidence_score": 3,
    "validation_summary": "Internal check reveals inconsistencies, while external check, although acknowledging plausibility, lacks definitive evidence to confirm the caption's specific claim.  The overall confidence is low due to a lack of verifiable details and external corroboration.  The image's context is uncertain,  pointing towards an out-of-context caption.  External checks are knowledge-based, resulting in a low confidence score of 3. The time period of WWII and the presence of landmines align with the possibility of the soldier carrying the donkey, yet there is insufficient evidence supporting this as the primary motivation of the photo. The French Foreign Legion's presence in Algeria during WWII is plausible but does not confirm the specific situation depicted in the image. Therefore, lack of specific contextual evidence indicates a high likelihood of an out-of-context caption.  Discrepancies are not directly between the results themselves, but between the claim and external evidence supporting it.  This means the absence of contradicting evidence does not establish the accuracy of the claim; instead, it highlights the lack of evidence to support it.  The lack of clarity about the image's context and supporting evidence leads to a low confidence level and an assessment that the caption is out-of-context. The fact that the image shows a soldier carrying a donkey might be related to the historical context of WWII and French Colonial Algeria, making it plausible. However, the lack of any hard evidence regarding a direct relationship makes this connection tentative and hence, the caption out of context. The lack of evidence, despite some plausible elements within the caption, significantly decreases the confidence score and leads to the conclusion of the caption being out of context. The absence of specific information linking the image to the caption is a critical factor in lowering the confidence score.  It is crucial to find sources verifying the scenario described in the caption or concrete evidence indicating a link between the picture's content and its alleged narrative. The internal check's negative result is not directly contradictory to the external assessment because the external assessment focuses on the plausibility of the caption, not its verifiability. Both assessments converge on the outcome that the caption lacks sufficient evidence to support its claims, leading to a conclusion of OOC=true and a low confidence score. The absence of verifiable external evidence is the primary reason for the low confidence score, although the plausibility of the event depicted slightly elevates it above zero. Despite the absence of direct contradictions between internal and external validation, the absence of strong supporting evidence significantly impacts the final assessment.  The inherent uncertainty around the image's context and the absence of confirmation of its specific narrative leads to this conclusion.  The combination of a negative internal consistency check and the lack of robust external verification contribute to this overall assessment of the caption as OOC = True. The validation process revealed a critical gap: while the caption's narrative (soldier carrying donkey to prevent landmine accidents) is reasonably plausible within the broader context of WWII, no external evidence confirms this precise scenario. The lack of external evidence heavily influences the confidence score, decreasing it significantly. The internal inconsistencies add further weight to this, resulting in the final OOC judgment. The plausibility alone cannot be a strong substitute for confirmed evidence. Therefore, the final result reflects the weight given to the lack of definitive evidence, regardless of its inherent plausibility.  Plausibility without verification is not enough for a high-confidence result.  This highlights the importance of external verification for accurate assessments and demonstrates why lack of external evidence results in a low confidence score, and a conclusion of OOC=True. Therefore, even if the events portrayed in the caption are possible, the absence of verifiable support necessitates a negative OOC conclusion. The focus is on verifiable evidence. This validates the claim that the lack of substantial evidence leads to a low confidence score and the OOC=true conclusion.  The caption may describe a possible scenario, but the lack of confirmation prevents a confident assessment. This again emphasizes the importance of verifiable evidence in historical assessments, and showcases that high confidence requires more than just plausible narratives. This supports the approach of giving a low confidence score and classifying the caption as OOC = True.  This highlights the crucial role of verifiable evidence, and the limitations of basing assessments solely on plausible narratives.  The validation process highlights that even plausible claims require strong external evidence for a high-confidence assessment.  This underscores the principle that high confidence requires solid proof, and lack thereof leads to a lower confidence score and possible OOC categorization. Therefore the final assessment is OOC=True because the caption's assertion lacks confirmation, indicating its out-of-context nature. This assessment emphasizes the vital importance of corroborating evidence in determining the accuracy of historical claims. Even seemingly plausible narratives, lacking verifiable evidence, cannot support a high-confidence positive assessment. The validation process showcases the significance of relying on confirmed sources.  The plausibility of the caption's content does not override the critical need for verifiable support; without it, the caption is inconclusive and, therefore, out-of-context."
  },
  "inference_time": 44.29091167449951
}