{
  "caption": "Eminem biopic '8 Mile' will return with a sequel in late 2016.",
  "ground_truth": 1,
  "internal_check": {
    "textual_entities": [
      {
        "entity": "B-MISC",
        "word": "8"
      },
      {
        "entity": "I-MISC",
        "word": "Mile"
      },
      {
        "entity": "I-MISC",
        "word": "2"
      }
    ],
    "result": {
      "verdict": false
    }
  },
  "external_check": {
    "candidates": [
      {
        "authors": [
          "Kim LaCapria"
        ],
        "title": "8 Mile Sequel Confirmed for December 2016?",
        "date": "2016-02-16T01:17:46",
        "content": 